[
    {
        "name": "Loid Forger",
        "anime": "Spy × Family",
        "image": "assets/loid_chibi.png",
        "traits": [
            "clever",
            "adaptable",
            "protective",
            "just",
            "emotionally distant",
            "intelligent",
            "strategic",
            "physically strong",
            "observant",
            "loyal",
            "disciplined",
            "focused",
            "secretive",
            "reserved",
            "perfectionist",
            "caring under pressure"
        ]
    },
    {
        "name": "Yuji Itadori",
        "anime": "Jujutsu Kaisen",
        "image": "assets/yuji_chibi.png",
        "traits": [
            "selfless",
            "physically strong",
            "brave",
            "naive",
            "loyal",
            "emotionally driven",
            "compassionate",
            "determined",
            "calm under pressure",
            "reckless",
            "empathetic",
            "morally conflicted",
            "protective",
            "resilient",
            "youthfully humorous"
        ]
    },
    {
        "name": "Osamu Dazai",
        "anime": "Bungou Stray Dogs",
        "image": "assets/dazai_chibi.png",
        "traits": [
            "strategic",
            "lazy genius",
            "fearless",
            "cool-headed",
            "loyal",
            "emotionally distant",
            "self-destructive",
            "darkly humorous",
            "reckless",
            "mysterious",
            "charming in odd ways",
            "detached",
            "complex moral code",
            "experienced",
            "manipulative for the greater good",
            "secretive"
        ]
    },
    {
        "name": "Satoru Gojo",
        "anime": "Jujutsu Kaisen",
        "image": "assets/gojo_chibi.png",
        "traits": [
            "playful",
            "cocky",
            "strategic",
            "genius",
            "powerful",
            "protective",
            "mentoring",
            "witty",
            "sarcastic",
            "overconfident",
            "arrogant",
            "disrespectful toward authority",
            "independent",
            "rebellious",
            "unmatched in strength",
            "loyal but selective",
            "charming",
            "sweet tooth"
        ]
    },
    {
        "name": "Tomoe",
        "anime": "Kamisama Kiss",
        "image": "assets/tomoe_chibi.png",
        "traits": [
            "cunning",
            "sarcastic",
            "loyal",
            "short-tempered",
            "protective",
            "tsundere",
            "mocking sense of humor",
            "secretly soft",
            "emotionally repressed",
            "strategic",
            "romantic but reluctant",
            "fiercely devoted",
            "powerful",
            "fox-like",
            "elegant",
            "roast master",
            "chaos suppressor",
            "overprotective",
            "grumpy on the outside, marshmallow on the inside"
        ]
    },
    {
        "name": "Suguru Geto",
        "anime": "Jujutsu Kaisen / Jujutsu Kaisen 0",
        "image": "assets/geto_chibi.png",
        "traits": [
            "intelligent",
            "composed",
            "charismatic",
            "philosophical",
            "extremist",
            "cult-leader energy",
            "refined",
            "ideological",
            "emotionally conflicted",
            "protective (towards his own)",
            "strategic thinker",
            "emotionally repressed",
            "aloof",
            "elitist",
            "conviction-driven",
            "quietly intense",
            "tragic hero turned villain",
            "loyal (to a fault)",
            "dangerously persuasive"
        ]
    },
    {
        "name": "Tanjiro Kamado",
        "anime": "Demon Slayer: Kimetsu no Yaiba",
        "image": "assets/tanjiro_chibi.png",
        "traits": [
            "kind",
            "empathetic",
            "determined",
            "bluntly honest",
            "protective",
            "sincere",
            "cannot lie well",
            "values all life",
            "rage against injustice",
            "disciplined",
            "compassionate",
            "hardworking",
            "emotionally strong",
            "family-oriented",
            "self-sacrificing",
            "gritty",
            "believes in redemption",
            "naive but pure-hearted"
        ]
    },
    {
        "name": "Levi Ackerman",
        "anime": "Attack on Titan",
        "image": "assets/levi_chibi.png",
        "traits": [
            "clean freak",
            "emotionally reserved",
            "dry sense of humor",
            "highly loyal",
            "values human life",
            "protective of comrades",
            "disdainful of authority",
            "morally grounded",
            "not arrogant despite talent",
            "empathetic under stoicism",
            "strong leadership skills",
            "brutally honest",
            "strategic thinker",
            "focused under pressure",
            "sadistic towards enemies",
            "deeply affected by loss"
        ]
    },
    {
        "name": "Roronoa Zoro",
        "anime": "One Piece",
        "image": "assets/zoro_chibi.png",
        "traits": [
            "determined",
            "blunt",
            "serious in battle",
            "loyal to friends",
            "prideful swordsman",
            "strong sense of honor",
            "easily irritated",
            "bad sense of direction",
            "frequently naps",
            "relentlessly trains",
            "ambitious",
            "protective",
            "respects strength",
            "competitive",
            "stoic"
        ]
    },
    {
        "name": "Nezuko Kamado",
        "anime": "Demon Slayer: Kimetsu no Yaiba",
        "image": "assets/Nezuko_chibi.png",
        "traits": [
            "kind",
            "selfless",
            "protective",
            "resistant to temptation",
            "strong-willed",
            "fierce in battle",
            "empathetic even as a demon",
            "childlike behavior",
            "loyal to Tanjiro",
            "emotional growth",
            "fearless",
            "high pain tolerance",
            "retains humanity",
            "quiet but expressive",
            "adorable but deadly"
        ]
    },
    {
        "name": "Monkey D. Luffy",
        "anime": "One Piece",
        "image": "assets/fluffy_chibi.png",
        "traits": [
            "carefree",
            "courageous",
            "extremely loyal",
            "protective of friends",
            "strong sense of justice",
            "occasionally reckless",
            "dream-driven",
            "never gives up",
            "loves freedom",
            "forgives easily",
            "natural leader",
            "naive but pure-hearted",
            "emotional but determined",
            "friendly with everyone",
            "fights for his crew's honor"
        ]
    },
    {
        "name": "Makima",
        "anime": "Chainsaw Man",
        "image": "assets/makima_chibi.png",
        "traits": [
            "calm under pressure",
            "professional",
            "manipulative",
            "calculating",
            "cold",
            "ruthless",
            "deceptively gentle",
            "Machiavellian",
            "emotionally detached",
            "psychologically strategic",
            "dominant",
            "charismatic in public",
            "secretly power-hungry",
            "uses fear as a weapon",
            "seeks control over all"
        ]
    },
    {
        "name": "Jinshi",
        "anime": "The Apothecary Diaries",
        "image": "assets/jinshi_chibi.png",
        "traits": [
            "extremely charming",
            "manipulative through beauty",
            "charismatic",
            "emotionally complex",
            "secretly insecure",
            "strategically clever",
            "expert in court politics",
            "graceful",
            "secretly lazy",
            "desires genuine affection",
            "self-aware but conflicted",
            "hides true self behind public mask",
            "attractive to everyone but focused on one person",
            "struggles with expectations",
            "uses perceived fragility as a tool"
        ]
    },
    {
        "name": "Maomao",
        "anime": "The Apothecary Diaries",
        "image": "assets/maomao_chibi.png",
        "traits": [
            "hyper-intelligent",
            "sarcastic",
            "practical",
            "emotionally detached",
            "poison expert",
            "medically brilliant",
            "pretends to be aloof",
            "secretly kind",
            "allergic to romance",
            "observant",
            "emotionally intelligent",
            "doesn’t tolerate nonsense",
            "introverted genius",
            "self-sacrificing in weird ways",
            "loves science more than people (but denies it)"
        ]
    },
    {
        "name": "Naruto Uzumaki",
        "anime": "Naruto / Naruto: Shippuden / Boruto: Naruto Next Generations",
        "image": "assets/naruto_chibi.png",
        "traits": [
            "hardworking underdog",
            "resilient",
            "loyal",
            "charismatic",
            "forgiving",
            "determined to prove himself",
            "prankster with a big heart",
            "natural leader",
            "emotional",
            "overcomes childhood trauma",
            "protective of friends and village",
            "believes in second chances",
            "sometimes impulsive",
            "massively overworks himself",
            "values bonds deeply",
            "inspiring through actions"
        ]
    },
    {
        "name": "Anya Forger",
        "anime": "Spy × Family",
        "image": "assets/anya_chibi.png",
        "traits": [
            "cheerful",
            "imaginative",
            "telepathic",
            "childishly brave",
            "playful",
            "resourceful",
            "emotionally reactive",
            "curious",
            "adorably dramatic",
            "low academic performance",
            "short attention span",
            "easily distracted",
            "low stamina",
            "sensitive to emotions around her",
            "deeply attached to her family",
            "creative problem-solver",
            "tries to help even if it goes wrong",
            "small but sneaky"
        ]
    }
]